pylext/base.py
pylext/importer.py
pylext/__init__.py
pylext/core/parse.cpython-39-x86_64-linux-gnu.so
pylext/core/__init__.py
pylext/core/grammar/python_3_8.py
pylext/core/grammar/__init__.py
pylext/magics/magics.py
pylext/magics/__init__.py
pylext/macros/operator.pyg
pylext/macros/__init__.py
pylext-0.2.1.dist-info/LICENSE
pylext-0.2.1.dist-info/METADATA
pylext-0.2.1.dist-info/top_level.txt
pylext-0.2.1.dist-info/RECORD
pylext-0.2.1.dist-info/WHEEL
